clickmod/__init__.py
clickmod/app.py
clickmod/errors.py
clickmod/middleware.py
clickmod-0.1.0.dist-info/METADATA
clickmod-0.1.0.dist-info/WHEEL
clickmod-0.1.0.dist-info/entry_points.txt
clickmod-0.1.0.dist-info/RECORD
